<?xml version="1.0" encoding="utf-8"?>
<Localization locale="en">
  <Description>A user account operation</Description>
  <EventDescriptions>
    <EventDescription id="168f59b5-2f63-23cf-2d2f-d1f067163fff">The administrator {subject.account.name} failed to delete the user account {object.account.name} on the security host {datafield1}</EventDescription>
    <EventDescription id="427dc47e-27f5-e96e-30c5-d015c038b66a">The administrator {subject.account.name} failed to add the user account {object.account.name} on the security host {datafield1}</EventDescription>
    <EventDescription id="f3187476-866a-ae3d-3dff-9668254c4a52">The administrator {subject.account.name} deleted the user account {object.account.name} on the security host {datafield1}</EventDescription>
    <EventDescription id="f5f6c94d-b03b-4f2f-f26c-2ace3953844c">The administrator {subject.account.name} added the user account {object.account.name} on the security host {datafield1}</EventDescription>
  </EventDescriptions>
</Localization>