<?xml version="1.0" encoding="utf-8"?>
<Localization locale="ru">
  <Description />
  <EventDescriptions>
    <EventDescription id="0b7868a1-bd0f-4f68-9591-fad6254b00ad">Пользователь {subject.name} добавил права ({object.value}) для доступа к устройству {datafield1} для пользователя {object.name} на узле {dst.host}</EventDescription>
    <EventDescription id="5302fb92-1947-4668-aa48-7da62bb99f88">Пользователь {subject.name} изменил права ({object.value}) для доступа к устройству {datafield1} для пользователя {object.name} на узле {dst.host}</EventDescription>
    <EventDescription id="b597e1c3-7acb-429c-87f5-19b9ef867227">Пользователь {subject.name} удалил права для доступа к устройству {datafield1} для пользователя {object.name} на узле {dst.host}</EventDescription>
  </EventDescriptions>
</Localization>