<?xml version="1.0" encoding="utf-8"?>
<Localization locale="ru">
  <Description>Пользователь вошел по паролю</Description>
  <EventDescriptions>
    <EventDescription id="4bdcfd06-8f0a-4401-be4e-89dcd629142e">Пароль пользователя {subject.account.name} принят на узле {event_src.host}</EventDescription>
    <EventDescription id="de27b494-6ae5-4627-83c7-264c3d669efd">Пароль пользователя {subject.account.name} отклонен на узле {event_src.host}</EventDescription>
  </EventDescriptions>
</Localization>