<?xml version="1.0" encoding="utf-8"?>
<Localization locale="ru">
  <Description>Пользователь открыл документ Microsoft Offiсe с макросом</Description>
  <EventDescriptions>
    <EventDescription id="0ac19269-3f3c-46f1-b6b1-c8e98e3f767c">Пользователь {subject.account.name} запустил Microsoft Offiсe {subject.process.name} и открыл документ "{object.name}" с макросом на узле {event_src.host}</EventDescription>
    <EventDescription id="451f7fba-7a36-445d-879f-20d1b1580332">Пользователь {subject.account.name} запустил Microsoft Offiсe {subject.process.name} и открыл документ с макросом на узле {event_src.host}</EventDescription>
  </EventDescriptions>
</Localization>