<?xml version="1.0" encoding="utf-8"?>
<Localization locale="ru">
  <Description>Подключение разрешено или заблокировано</Description>
  <EventDescriptions>
    <EventDescription id="020af2a3-6eb6-24bf-4ab5-d042f8ef7966">Разрешено подключение с адреса {src.mac} к адресу {dst.mac} на узле {event_src.host}</EventDescription>
    <EventDescription id="b5f9d37e-9643-5c9c-f5de-e6d8c63abf99">Заблокировано подключение с адреса {src.mac} к адресу {dst.mac} на узле {event_src.host}</EventDescription>
    <EventDescription id="d4b21e2b-2f83-e0e5-adfa-7848f8e47243">Разрешено подключение по протоколу {protocol} с узла {src.host} к узлу {dst.host} на узле {event_src.host}</EventDescription>
    <EventDescription id="e70cb465-17f5-6282-548d-08c3490acedf">Заблокировано подключение по протоколу {protocol} с узла {src.host}:{src.port} к узлу {dst.host}:{dst.port} на узле {event_src.host}</EventDescription>
    <EventDescription id="ef883545-3ad5-0f39-33f5-ba2a3fb1c31f">Разрешено подключение по протоколу {protocol} с узла {src.host}:{src.port} к узлу {dst.host}:{dst.port} на узле {event_src.host}</EventDescription>
    <EventDescription id="f56e387e-d6cb-b02a-28a0-05f74626f943">Заблокировано подключение по протоколу {protocol} с узла {src.host} к узлу {dst.host} на узле {event_src.host}</EventDescription>
  </EventDescriptions>
</Localization>