<?xml version="1.0" encoding="utf-8"?>
<Localization locale="en">
  <Description>Attempt to detach virtual machine management tools</Description>
  <EventDescriptions>
    <EventDescription id="39f6ffbe-50da-2a00-4861-ac37ca5a7c2d">User {subject.account.name} could not detach management tools for virtual machine {datafield1} on host {event_src.host}</EventDescription>
    <EventDescription id="b87d1322-1d6d-1dd4-d8f3-0122046c002d">User {subject.account.name} detached management tools for virtual machine {datafield1} on host {event_src.host}</EventDescription>
  </EventDescriptions>
</Localization>