<?xml version="1.0" encoding="utf-8"?>
<Localization locale="ru">
  <Description>PT Sandbox среагировал на один из файлов во время сессии анализа</Description>
  <EventDescriptions>
    <EventDescription id="2311ff39-2731-9842-8f7e-5a155129e5c2">PT Sandbox провел анализ файла c хеш-суммой {object.hash} с вердиктом "{reason}"</EventDescription>
    <EventDescription id="2934554c-2101-2570-1977-20661d158a69">PT Sandbox провел анализ файла {object.storage.name} с вердиктом "{reason}"</EventDescription>
  </EventDescriptions>
</Localization>