<?xml version="1.0" encoding="utf-8"?>
<Localization locale="ru">
  <Description>Выполнено большое количество команд для сбора информации о системе. Возможен автоматизированный сбор</Description>
  <EventDescriptions>
    <EventDescription id="72d237c2-7492-2f89-fcf2-5e903cb78613">Пользователь {subject.account.name} после подключения по SSH выполнил большое количество команд для сбора информации о системе на узле {event_src.host}</EventDescription>
    <EventDescription id="e9cd45e3-15db-dca8-f8ea-49f546a23e9b">Пользователь {subject.account.name} выполнил большое количество команд для сбора информации о системе на узле {event_src.host}</EventDescription>
  </EventDescriptions>
</Localization>