<?xml version="1.0" encoding="utf-8"?>
<Localization locale="en">
  <Description>Dhcp request message</Description>
  <EventDescriptions>
    <EventDescription id="87484cac-90a1-45e6-ac19-1670106ac67d">A host with MAC address {src.mac} requested IP address {assigned_src_ip} from host {event_src.host}</EventDescription>
    <EventDescription id="ef6ee535-677f-40a1-b786-a09d5bdb2133">A host with MAC address {src.mac} failed to get IP address {assigned_src_ip} from host {event_src.host}. Reason: {reason}</EventDescription>
  </EventDescriptions>
</Localization>