<?xml version="1.0" encoding="utf-8"?>
<Localization locale="ru">
  <Description>Объект не удален</Description>
  <EventDescriptions>
    <EventDescription id="37173bf6-68a0-70e7-932b-bca9cb977bfe">Не удалось удалить объект {object.name} с путем {object.path} на узле {src.host}, так как объект не найден</EventDescription>
    <EventDescription id="3fda401e-ddf1-9c81-52e3-2111c8acf1ff">Не удалось удалить объект {object.name} с путем {object.path} на узле {event_src.host}, так как объект не найден</EventDescription>
  </EventDescriptions>
</Localization>