<?xml version="1.0" encoding="utf-8"?>
<Localization locale="en">
  <Description>A user changed a predefined data value</Description>
  <EventDescriptions>
    <EventDescription id="b04be67e-6e9e-4aec-b964-fbaf7ef87d53">A user from host {src.host} changed database predefined data value "{object.property}" to "{object.new_value}" on host {event_src.host}</EventDescription>
    <EventDescription id="d277a966-3171-4423-a004-0129f6cac166">User {subject.application.account.name} from host {src.host} changed database predefined data value "{object.property}" to "{object.new_value}" on host {event_src.host}</EventDescription>
  </EventDescriptions>
</Localization>