<?xml version="1.0" encoding="utf-8"?>
<Localization locale="ru">
  <Description>Управление шаблонами конфигурации сборки</Description>
  <EventDescriptions>
    <EventDescription id="0ef5e0c5-f937-4f1e-83f1-40f519f16916">Шаблон конфигурации сборки {object.fullpath} создан на узле {event_src.host}</EventDescription>
    <EventDescription id="3749513b-eab3-4d24-b190-a5bc728c88b6">Шаблон конфигурации сборки {object.fullpath} изменен на узле {event_src.host}</EventDescription>
    <EventDescription id="517f0d8b-c529-4288-b74c-bf440a8c735e">Шаблон конфигурации сборки {object.fullpath} удален на узле {event_src.host}</EventDescription>
    <EventDescription id="b7c3c170-befc-4b90-8e09-f68807bec542">Шаблон конфигурации сборки {object.fullpath} скопирован на узле {event_src.host}</EventDescription>
  </EventDescriptions>
</Localization>