<?xml version="1.0" encoding="utf-8"?>
<Localization locale="en">
  <Description>Configuration audit</Description>
  <EventDescriptions>
    <EventDescription id="5dcafbda-fa9d-44db-ba99-5533807e7457">The configuration "{object.name}" failed to pass the check for compliance with the rule "{subject.name}" on host {src.host}</EventDescription>
    <EventDescription id="8f69870c-b564-4b6a-aaba-9a37b2903956">The rule "{object.name}" had failed on host {src.host}. Reason: {reason}</EventDescription>
    <EventDescription id="a580835f-95ec-41f3-a2ca-6e91eb626115">The configuration "{object.name}" is checked for compliance with the rule "{subject.name}" on host {src.host}</EventDescription>
    <EventDescription id="e68edb10-8192-435c-bb38-e405ffafccd6">Failed to start checking the configuration "{object.name}" for compliance with the rule "{subject.name}" on host {src.host}. Reason: {reason}</EventDescription>
    <EventDescription id="ebbe7890-aad5-4de6-b75a-6855c10b4a6a">The rule "{object.name}" is checked to extract information from the object "{datafield10}" on host {src.host}</EventDescription>
  </EventDescriptions>
</Localization>