<?xml version="1.0" encoding="utf-8"?>
<Localization locale="ru">
  <Description>Запущен браузер с функцией удаленной отладки, что может быть использовано для переадресации трафика на машину злоумышленника</Description>
  <EventDescriptions>
    <EventDescription id="b45debd4-4ad8-cbd4-656c-f9b2ccb30043">Браузер {object.process.name} запущен с функцией удаленной отладки на адрес 127.0.0.1:{dst.port} и переадресацией на порт {src.port} от имени пользователя {subject.account.name} на узле {event_src.host}</EventDescription>
    <EventDescription id="f3a3a78e-484a-dca3-27e6-38fe475c611d">Возможно, браузер {object.process.name} запущен с функцией удаленной отладки на адрес 127.0.0.1:{dst.port} от имени пользователя {subject.account.name} на узле {event_src.host}</EventDescription>
  </EventDescriptions>
</Localization>