<?xml version="1.0" encoding="utf-8"?>
<Localization locale="en">
  <Description>Participants_actions</Description>
  <EventDescriptions>
    <EventDescription id="3a2aad9e-d74d-48e9-b00e-4d0c085bca7e">The participant account {object.name} is created on host {event_src.host}</EventDescription>
    <EventDescription id="83ed00e7-42b8-44d8-a58e-8fb75777c471">The participant account {object.name} is activated on host {event_src.host}</EventDescription>
    <EventDescription id="9c860101-b75a-491c-bf1f-f60c7e0a7404">The participant account {object.name} is modified on host {event_src.host}</EventDescription>
    <EventDescription id="a004cd9d-37ec-4088-b34c-3a2cacd6485c">The participant account {object.name} is viewed on host {event_src.host}</EventDescription>
    <EventDescription id="eeebfe50-cab7-449e-9823-53ea53e032e0">The participant account {object.name} is deactivated on host {event_src.host}</EventDescription>
  </EventDescriptions>
</Localization>