<?xml version="1.0" encoding="utf-8"?>
<Localization locale="ru">
  <Description>Попытка изменить конфигурацию брандмауэра Windows</Description>
  <EventDescriptions>
    <EventDescription id="6a6aa02e-9eb3-0aac-26a1-43ad979f7974">Пользователь {subject.account.name} попытался изменить конфигурацию брандмауэра Windows на узле {event_src.host}</EventDescription>
    <EventDescription id="b7e2b1c5-991b-b0bb-df77-09e6d81d5cbb">Попытка изменить конфигурацию брандмауэра Windows на узле {event_src.host}</EventDescription>
  </EventDescriptions>
</Localization>