<?xml version="1.0" encoding="utf-8"?>
<Localization locale="en">
  <Description>A policy application error</Description>
  <EventDescriptions>
    <EventDescription id="2cc159b5-8688-4244-bba9-3a4165f4e00a">Error applying the policy "{object.name}" during authentication of a user on host {event_src.host}</EventDescription>
    <EventDescription id="eadaf984-0dad-464d-b224-becf7f194a45">Error applying the policy "{object.name}" during authentication of the user {datafield2} on host {event_src.host}</EventDescription>
  </EventDescriptions>
</Localization>