<?xml version="1.0" encoding="utf-8"?>
<Localization locale="ru">
  <Description />
  <EventDescriptions>
    <EventDescription id="095f9ee6-fdba-424e-bd93-02db14407f2f">Пользователь {subject.account.name} остановил службу {object.name}</EventDescription>
    <EventDescription id="19da27d0-f204-47a8-bf85-1b9d8d6aa9e5">Пользователь {subject.account.name} перезапустил службу {object.name}</EventDescription>
    <EventDescription id="92fca5b6-2898-42dc-bbe6-6d261398b8d5">Пользователь {subject.account.name} запустил службу {object.name}</EventDescription>
  </EventDescriptions>
</Localization>