<?xml version="1.0" encoding="utf-8"?>
<Localization locale="ru">
  <Description>Отключение системы контроля доступа на узле. Атакующие могут использовать отключение, чтобы скрыть свою активность</Description>
  <EventDescriptions>
    <EventDescription id="99e973ed-edc1-4d47-8d18-68d2e83c6752">Пользователь {subject.account.name} отключил систему SELinux на узле {event_src.host}</EventDescription>
    <EventDescription id="bb92e851-d5fc-814a-085c-085b5818dd68">Пользователь {subject.account.name} изменил конфигурацию системы SELinux и перезапустил ее на узле {event_src.host}</EventDescription>
  </EventDescriptions>
</Localization>