<?xml version="1.0" encoding="utf-8"?>
<Localization locale="en">
  <Description>A user changed file basic attributes</Description>
  <EventDescriptions>
    <EventDescription id="054321cd-c501-80d7-b9d4-e878aa894dcc">The user {subject.account.name} changed the basic attributes of file {object.name} on host {event_src.host}</EventDescription>
    <EventDescription id="5127e570-6cfb-bdef-3df9-a855e2857fe0">The user {subject.account.name} changed the file basic attributes on path {object.path} on host {event_src.host}</EventDescription>
  </EventDescriptions>
</Localization>