<?xml version="1.0" encoding="utf-8"?>
<Localization locale="en">
  <Description>Attempt to delete an account</Description>
  <EventDescriptions>
    <EventDescription id="39c33ffb-1427-9e14-6350-c84b98bf58aa">User {subject.account.name} deleted account {object.account.name} with rights {object.account.privileges} on host {event_src.host}</EventDescription>
    <EventDescription id="8371a172-a711-8778-28fb-061deda8348e">User {subject.account.name} could not delete account {object.account.name} with rights {object.account.privileges} on host {event_src.host}</EventDescription>
  </EventDescriptions>
</Localization>