<?xml version="1.0" encoding="utf-8"?>
<Localization locale="ru">
  <Description>Подбор пароля к учетным записям для сетевого устройства Eltex</Description>
  <EventDescriptions>
    <EventDescription id="37bde1ae-0bee-d698-5ab2-e0a45810cb15">Попытки подобрать пароль к учетной записи {subject.account.name} для сетевого устройства {event_src.vendor} на узле {event_src.host}. Количество попыток входа: {datafield1}</EventDescription>
    <EventDescription id="ae904454-4190-93a6-ca14-0ba72c6a6d6a">Подобран пароль к учетной записи {subject.account.name} с узла {src.host} для сетевого устройства {event_src.vendor} на узле {event_src.host}. Количество неудачных попыток входа: {datafield1}</EventDescription>
  </EventDescriptions>
</Localization>