<?xml version="1.0" encoding="utf-8"?>
<Localization locale="ru">
  <Description>Передача зоны DNS от недоверенного узла</Description>
  <EventDescriptions>
    <EventDescription id="2f7ce0a1-b84d-e4e2-8504-97c6739300e4">Запрещена передача зоны {object.name} по TCP-запросу AXFR от недоверенного узла {src.host} на узел {event_src.host}</EventDescription>
    <EventDescription id="56e287a0-0418-0d0c-52b5-ef9a896f2a91">Начата передача зоны {object.name} по TCP-запросу AXFR от недоверенного узла {src.host} на узел {event_src.host}</EventDescription>
  </EventDescriptions>
</Localization>