<?xml version="1.0" encoding="utf-8"?>
<Localization locale="en">
  <Description>A user elevated privileges</Description>
  <EventDescriptions>
    <EventDescription id="869afca5-ed9b-46cd-ad71-e0313849f657">The user {subject.account.name} failed to elevate privileges to execute a command on host {event_src.host}</EventDescription>
    <EventDescription id="f54a5088-8ea8-4299-936c-ab9cbe88f379">The user {subject.account.name} elevated privileges to execute a command on host {event_src.host}</EventDescription>
  </EventDescriptions>
</Localization>