<?xml version="1.0" encoding="utf-8"?>
<Localization locale="en">
  <Description>Attempt to delete a firewall rule</Description>
  <EventDescriptions>
    <EventDescription id="01e51f93-2a10-b39d-24aa-92f713f2458f">Attempt to delete a firewall rule. Result: {datafield3} ({object.state}).</EventDescription>
    <EventDescription id="2a1aede7-544b-8777-253c-6cadd4209c08">Attempt to delete a firewall rule. Result: {datafield3} ({object.state}). Comment: {reason}.</EventDescription>
  </EventDescriptions>
</Localization>