<?xml version="1.0" encoding="utf-8"?>
<Localization locale="en">
  <Description>A connection is rejected</Description>
  <EventDescriptions>
    <EventDescription id="2890f230-847c-4aa1-a540-bd673ee0c253">The connection of the user {object.account.name} established from host {src.host} is rejected due to the rule "{event_src.rule}"</EventDescription>
    <EventDescription id="522a0cd6-b242-43c9-8cf0-a9a232835724">The connection of the user {object.account.name} established from host {src.host} to host {dst.host}:{dst.port} is rejected due to the rule "{event_src.rule}"</EventDescription>
    <EventDescription id="b6cb7de3-3c91-4bdb-bfc1-5259aa5e1a13">A connection from host {src.host} is rejected due to the rule "{event_src.rule}"</EventDescription>
  </EventDescriptions>
</Localization>