<?xml version="1.0" encoding="utf-8"?>
<Localization locale="ru">
  <Description>Пользователь вошел в систему</Description>
  <EventDescriptions>
    <EventDescription id="f1089c24-85e1-946f-1e91-53f266ef68eb">Пользователь {subject.account.name} удаленно вошел в систему на узле {event_src.host}</EventDescription>
    <EventDescription id="f4610432-7c39-b666-ebc7-ddbf958d5213">Пользователь {subject.account.name} локально вошел в систему на узле {event_src.host}</EventDescription>
  </EventDescriptions>
</Localization>