<?xml version="1.0" encoding="utf-8"?>
<Localization locale="en">
  <Description>An administration server is started or stopped, or a task is started</Description>
  <EventDescriptions>
    <EventDescription id="3ebbb5f7-8f4d-4cf5-b8fb-ccdf8075af76">The task "{object.name}" is started on host {event_src.host}</EventDescription>
    <EventDescription id="4e8461c8-39e2-456d-ac5c-ddfbe7b6dc77">The administration server is started on host {event_src.host}</EventDescription>
    <EventDescription id="a1b50c7b-349e-43f8-a056-629b19b506c1">The administration server is stopped on host {event_src.host}</EventDescription>
  </EventDescriptions>
</Localization>