<?xml version="1.0" encoding="utf-8"?>
<Localization locale="en">
  <Description>A PT AF rule was triggered</Description>
  <EventDescriptions>
    <EventDescription id="22dbaaa2-fbf7-9af4-360f-40af72069573">PT AF correlation rule "{subject.name}" was triggered on host {event_src.host}</EventDescription>
    <EventDescription id="654dee10-6f53-b605-5ddd-9aa8272a1677">{numfield1} PT AF rules were triggered within one session on host {event_src.host}</EventDescription>
    <EventDescription id="803b2aca-a9f6-a087-551a-f30536246395">Rule "{alert.context}" was triggered on host {event_src.host}</EventDescription>
  </EventDescriptions>
</Localization>