<?xml version="1.0" encoding="utf-8"?>
<Localization locale="ru">
  <Description>Управление запросами на слияние</Description>
  <EventDescriptions>
    <EventDescription id="00d92f00-aa94-4307-be70-46251c4f1e2f">Пользователь {subject.account.name} изменил статус запроса на слияние !{numfield3} для проекта {datafield2}/{datafield1} на "Draft" на узле {event_src.host}</EventDescription>
    <EventDescription id="3a92e66e-4adb-47c7-9c79-ad62e75aac08">Не удалось запустить слияние веток "{object.value}" и "{object.new_value}" по запросу !{numfield3} для проекта {datafield2}/{datafield1} на узле {event_src.host}</EventDescription>
    <EventDescription id="417f6e39-1a34-415e-aeb9-46abf57b521c">Пользователь {subject.account.name} изменил запрос на слияние !{numfield3} для проекта {datafield2}/{datafield1} на узле {event_src.host}</EventDescription>
    <EventDescription id="45169820-dedc-40b4-90fb-46263295661f">Пользователь {subject.account.name} закрыл запрос на слияние !{numfield3} для проекта {datafield2}/{datafield1} на узле {event_src.host}</EventDescription>
    <EventDescription id="84509080-bebe-47c1-b503-bd8b6207f5dc">Пользователь {subject.account.name} перебазировал запрос на слияние !{numfield3} для проекта {datafield2}/{datafield1} на узле {event_src.host}</EventDescription>
    <EventDescription id="88e716ae-bd8e-4edd-b165-4d567bd2c817">Пользователь {subject.account.name} заново открыл запрос на слияние !{numfield3} для проекта {datafield2}/{datafield1} на узле {event_src.host}</EventDescription>
    <EventDescription id="8e6d0030-f876-4f8f-9a0b-342faaf82a00">Не удалось закрыть запрос на слияние !{numfield3} для проекта {datafield2}/{datafield1} на узле {event_src.host}</EventDescription>
    <EventDescription id="8fa48416-14c9-4a12-bc15-17e088e9802e">Не удалось изменить запрос на слияние !{numfield3} для проекта {datafield2}/{datafield1} на узле {event_src.host}</EventDescription>
    <EventDescription id="a814a8b0-0a3c-43ad-bd88-c9f8fa46f77b">Не удалось изменить статус запроса на слияние !{numfield3} для проекта {datafield2}/{datafield1} на "Draft" на узле {event_src.host}</EventDescription>
    <EventDescription id="bcb6bc4b-0702-7af7-73f5-5a9439e0b63f">Пользователь {subject.account.name} запустил слияние веток "{object.value}" и "{object.new_value}" по запросу !{numfield3} для проекта {datafield2}/{datafield1} на узле {event_src.host}</EventDescription>
    <EventDescription id="c688fbd0-349c-478b-a180-55d0fbbd807c">Не удалось удалить запрос на слияние !{numfield3} для проекта {datafield2}/{datafield1} на узле {event_src.host}</EventDescription>
    <EventDescription id="c812c563-50dc-458b-bb87-a475392e2760">Не удалось заново открыть запрос на слияние !{numfield3} для проекта {datafield2}/{datafield1} на узле {event_src.host}</EventDescription>
    <EventDescription id="d936968c-e47e-4460-899a-32ab3faf11fe">Не удалось изменить статус запроса на слияние !{numfield3} для проекта {datafield2}/{datafield1} на "Ready" на узле {event_src.host}</EventDescription>
    <EventDescription id="e1dd0764-8803-47e3-b6c2-07a469cdce71">Пользователь {subject.account.name} удалил запрос на слияние !{numfield3} для проекта {datafield2}/{datafield1} на узле {event_src.host}</EventDescription>
    <EventDescription id="e826b235-c2cf-466f-9ce2-730ce219b8b5">Не удалось перебазировать запрос на слияние !{numfield3} для проекта {datafield2}/{datafield1} на узле {event_src.host}</EventDescription>
    <EventDescription id="f505827b-a72d-494f-a7d1-285b2b76872d">Пользователь {subject.account.name} изменил статус запроса на слияние !{numfield3} для проекта {datafield2}/{datafield1} на "Ready" на узле {event_src.host}</EventDescription>
  </EventDescriptions>
</Localization>