<?xml version="1.0" encoding="utf-8"?>
<Localization locale="en">
  <Description>Role deleted</Description>
  <EventDescriptions>
    <EventDescription id="b6a08845-e237-41af-961a-a7f3257af8af">The user {subject.name} deleted the role "{object.name}" on host {event_src.host}</EventDescription>
    <EventDescription id="b709876d-dc75-42e0-a8da-5d9af895eef7">The user {subject.name} failed to delete the role "{object.name}" on host {event_src.host}. Reason: {reason}</EventDescription>
  </EventDescriptions>
</Localization>