<?xml version="1.0" encoding="utf-8"?>
<Localization locale="en">
  <Description>A user changed a database configuration</Description>
  <EventDescriptions>
    <EventDescription id="754c556c-9c37-450b-98ff-f82408245a58">User {subject.application.account.name} changed a database configuration while working in Designer mode on host {event_src.host}</EventDescription>
    <EventDescription id="a46b7ea6-a121-4c2a-b8d7-605ff91233b5">A user changed a database configuration while working in Designer mode on host {event_src.host}</EventDescription>
  </EventDescriptions>
</Localization>