<?xml version="1.0" encoding="utf-8"?>
<Localization locale="en">
  <Description>Password bruteforcing for accounts for a Cisco firewall</Description>
  <EventDescriptions>
    <EventDescription id="cce0e512-5dd0-4e1e-2542-414e7f45b72a">Password bruteforcing attempts for account {subject.account.name} from host {src.host} for a {event_src.vendor} firewall on host {event_src.host}. Number of login attempts: {datafield1}.</EventDescription>
    <EventDescription id="e9c8e09a-97f9-0ba4-546c-1cae444f9657">Successful password bruteforcing for account {subject.account.name} from host {src.host} for a {event_src.vendor} firewall on host {event_src.host}. Number of failed login attempts: {datafield1}.</EventDescription>
  </EventDescriptions>
</Localization>