<?xml version="1.0" encoding="utf-8"?>
<Localization locale="en">
  <Description>A user is connecting to a host</Description>
  <EventDescriptions>
    <EventDescription id="496c78db-c24c-438d-a304-f5176966ce09">The user {subject.account.name} from host {src.host} is connecting to host {event_src.host} using cipher {object.value}</EventDescription>
    <EventDescription id="8579d8d6-961e-4650-867f-102517b4915e">A user from host {event_src.host} is connecting to OpenVPN server using cipher {object.value}</EventDescription>
  </EventDescriptions>
</Localization>