<?xml version="1.0" encoding="utf-8"?>
<Localization locale="en">
  <Description>Suspicious logon to an application with no specific profiling rules. Authentication data differs from the collected profile.</Description>
  <EventDescriptions>
    <EventDescription id="84420088-3b29-4f41-a39b-d89f1728de3e">New user {subject.account.name} from host {src.host} logged in to application "{event_src.title}" on host {event_src.host}. The user is missing from the collected profile.</EventDescription>
    <EventDescription id="ab9d9354-4877-4e76-86b2-cc30dfa45f68">User {subject.account.name} from new host {src.host} logged in to application "{event_src.title}" on host {event_src.host}. The address is missing from the collected profile.</EventDescription>
  </EventDescriptions>
</Localization>