<?xml version="1.0" encoding="utf-8"?>
<Localization locale="en">
  <Description>SMTP request</Description>
  <EventDescriptions>
    <EventDescription id="0890b561-d3dc-4c26-b753-3f91dd4246ba">A message from the user {subject.name} to the {datafield2} users from host {src.host} to host {dst.host} passed through host {event_src.host}</EventDescription>
    <EventDescription id="bb97b391-a044-45d2-abc0-d13caa37b032">A message from the user {subject.name} to the user {object.value} from host {src.host} to host {dst.host} passed through host {event_src.host}</EventDescription>
  </EventDescriptions>
</Localization>