<?xml version="1.0" encoding="utf-8"?>
<Localization locale="en">
  <Description>Action on a page</Description>
  <EventDescriptions>
    <EventDescription id="6f5206a0-670f-d22f-4d9f-2e7a05513fb2">A user closed page "{object.name}" on host {event_src.host}</EventDescription>
    <EventDescription id="878fa9c7-0f7a-2cb2-8028-0dabf4cd7de4">A user opened page "{object.name}" on host {event_src.host}</EventDescription>
    <EventDescription id="e9c9457e-d92d-4e08-1ba5-fd6f78cb42e2">A user performed action "{object.value}" on page "{object.name}" on host {event_src.host}</EventDescription>
  </EventDescriptions>
</Localization>